spothot/__init__.py
spothot/app.py
spothot/main.py
spothot-2.7.dist-info/METADATA
spothot-2.7.dist-info/WHEEL
spothot-2.7.dist-info/entry_points.txt
spothot-2.7.dist-info/top_level.txt
spothot-2.7.dist-info/RECORD
