Metadata-Version: 2.1
Name: spothot
Version: 2.7
Summary: A package to set up Raspberry Pi as a Wi-Fi hotspot
Home-page: https://github.com/skshadan/spothot
Author: Shadan Khan
Author-email: shadankhantech@gmail.com
Classifier: Programming Language :: Python :: 3
Classifier: License :: OSI Approved :: MIT License
Classifier: Operating System :: OS Independent
Requires-Python: >=3.6
Requires-Dist: Flask
